coupons/__init__.py
coupons/admin.py
coupons/filters.py
coupons/forms.py
coupons/models.py
coupons/serializers.py
coupons/settings.py
coupons/urls.py
coupons/views.py
coupons/locale/de/LC_MESSAGES/django.mo
coupons/locale/de/LC_MESSAGES/django.po
coupons/migrations/0001_initial.py
coupons/migrations/__init__.py
coupons/south_migrations/0001_initial.py
coupons/south_migrations/0002_auto__add_field_coupon_valid_until.py
coupons/south_migrations/0003_auto__add_campaign__add_field_coupon_campaign.py
coupons/south_migrations/0004_auto__add_couponuser__add_field_coupon_user_limit.py
coupons/south_migrations/0005_coupon_users.py
coupons/south_migrations/0006_auto__del_field_coupon_redeemed_at__del_field_coupon_user.py
coupons/south_migrations/0007_auto__add_unique_couponuser_coupon_user.py
coupons/south_migrations/__init__.py
coupons/templates/admin/generate_coupons.html
coupons/tests/__init__.py
coupons/tests/settings.py
coupons/tests/test_admin.py
coupons/tests/test_forms.py
coupons/tests/test_models.py
coupons/tests/test_use_cases.py
django2_coupons-3.0.0.dist-info/LICENSE
django2_coupons-3.0.0.dist-info/METADATA
django2_coupons-3.0.0.dist-info/WHEEL
django2_coupons-3.0.0.dist-info/top_level.txt
django2_coupons-3.0.0.dist-info/RECORD
