Metadata-Version: 2.1
Name: django2-coupons
Version: 3.0.0
Summary: A reuseable Django application for coupon gereration and handling.
Home-page: https://github.com/ramwin/django-coupons
Author: byteweaver & Xiang Wang
Author-email: ramwin@qq.com
License: Copyright (c) 2013, byteweaver
Requires-Dist: django (>=1.11)
Requires-Dist: djangorestframework
Requires-Dist: django-filter
